pareng_boyong/__init__.py
pareng_boyong/cli/__init__.py
pareng_boyong/cli/chat.py
pareng_boyong/cli/config.py
pareng_boyong/cli/main.py
pareng_boyong/cli/setup.py
pareng_boyong/cli/web.py
pareng_boyong/core/__init__.py
pareng_boyong/core/agent.py
pareng_boyong/core/config.py
pareng_boyong/core/exceptions.py
pareng_boyong/core/tools.py
pareng_boyong/cultural/__init__.py
pareng_boyong/cultural/greetings.py
pareng_boyong/cultural/identity.py
pareng_boyong/cultural/language.py
pareng_boyong/cultural/values.py
pareng_boyong/helpers/__init__.py
pareng_boyong/helpers/cost_optimizer.py
pareng_boyong/helpers/system_monitor.py
pareng_boyong-1.0.0.dist-info/licenses/LICENSE
pareng_boyong-1.0.0.dist-info/METADATA
pareng_boyong-1.0.0.dist-info/WHEEL
pareng_boyong-1.0.0.dist-info/entry_points.txt
pareng_boyong-1.0.0.dist-info/top_level.txt
pareng_boyong-1.0.0.dist-info/RECORD
