Metadata-Version: 2.4
Name: pareng-boyong
Version: 1.0.0
Summary: Pareng Boyong - Your Intelligent Filipino AI Agent and Coding Assistant
Home-page: https://github.com/innovatehub-ph/pareng-boyong
Author: InnovateHub PH
Author-email: InnovateHub PH <info@innovatehub.ph>
Maintainer-email: Pareng Boyong Development Team <dev@innovatehub.ph>
License: MIT
Project-URL: Homepage, https://github.com/innovatehub-ph/pareng-boyong
Project-URL: Documentation, https://pareng-boyong.readthedocs.io
Project-URL: Repository, https://github.com/innovatehub-ph/pareng-boyong.git
Project-URL: Bug Tracker, https://github.com/innovatehub-ph/pareng-boyong/issues
Project-URL: Changelog, https://github.com/innovatehub-ph/pareng-boyong/blob/main/CHANGELOG.md
Keywords: ai,agent,filipino,coding-assistant,multimodal,cost-optimization,agent-zero,pinoy-ai,tts,cli
Classifier: Development Status :: 4 - Beta
Classifier: Intended Audience :: Developers
Classifier: Intended Audience :: System Administrators
Classifier: License :: OSI Approved :: MIT License
Classifier: Operating System :: OS Independent
Classifier: Programming Language :: Python :: 3
Classifier: Programming Language :: Python :: 3.8
Classifier: Programming Language :: Python :: 3.9
Classifier: Programming Language :: Python :: 3.10
Classifier: Programming Language :: Python :: 3.11
Classifier: Programming Language :: Python :: 3.12
Classifier: Topic :: Software Development :: Code Generators
Classifier: Topic :: Scientific/Engineering :: Artificial Intelligence
Classifier: Topic :: System :: Systems Administration
Classifier: Topic :: Text Processing :: Linguistic
Classifier: Natural Language :: English
Requires-Python: >=3.8
License-File: LICENSE
Requires-Dist: click>=8.0.0
Requires-Dist: python-dotenv>=1.0.0
Requires-Dist: pydantic>=2.0.0
Requires-Dist: rich>=13.0.0
Requires-Dist: typer>=0.9.0
Requires-Dist: httpx>=0.25.0
Requires-Dist: asyncio-throttle>=1.0.0
Requires-Dist: tiktoken>=0.5.0
Requires-Dist: nest-asyncio>=1.6.0
Requires-Dist: psutil>=5.9.0
Requires-Dist: pyyaml>=6.0.0
Requires-Dist: pytz>=2023.3
Provides-Extra: ai
Requires-Dist: openai>=1.3.0; extra == "ai"
Requires-Dist: anthropic>=0.3.0; extra == "ai"
Requires-Dist: litellm>=1.40.0; extra == "ai"
Requires-Dist: sentence-transformers>=2.2.0; extra == "ai"
Requires-Dist: faiss-cpu>=1.7.0; extra == "ai"
Provides-Extra: multimedia
Requires-Dist: pillow>=10.0.0; extra == "multimedia"
Requires-Dist: opencv-python>=4.8.0; extra == "multimedia"
Requires-Dist: moviepy>=1.0.3; extra == "multimedia"
Requires-Dist: imageio>=2.31.0; extra == "multimedia"
Requires-Dist: requests>=2.31.0; extra == "multimedia"
Provides-Extra: filipino
Requires-Dist: soundfile>=0.12.0; extra == "filipino"
Requires-Dist: librosa>=0.10.0; extra == "filipino"
Requires-Dist: phonemizer>=3.2.0; extra == "filipino"
Requires-Dist: espeak-ng>=1.51; extra == "filipino"
Provides-Extra: web
Requires-Dist: flask>=2.3.0; extra == "web"
Requires-Dist: flask-cors>=4.0.0; extra == "web"
Requires-Dist: websockets>=11.0.0; extra == "web"
Requires-Dist: jinja2>=3.1.0; extra == "web"
Provides-Extra: dev
Requires-Dist: pytest>=7.4.0; extra == "dev"
Requires-Dist: pytest-asyncio>=0.21.0; extra == "dev"
Requires-Dist: black>=23.0.0; extra == "dev"
Requires-Dist: flake8>=6.0.0; extra == "dev"
Requires-Dist: mypy>=1.5.0; extra == "dev"
Requires-Dist: pre-commit>=3.4.0; extra == "dev"
Provides-Extra: full
Requires-Dist: pareng-boyong[ai,filipino,multimedia,web]; extra == "full"
Dynamic: author
Dynamic: home-page
Dynamic: license-file
Dynamic: requires-python
